AUTHORS
CHANGES.rst
CONTRIBUTING.rst
LICENSE
LICENSE.md
MANIFEST.in
Makefile
README.md
setup.py
choppy/__init__.py
choppy/check_utils.py
choppy/choppy_pipe.py
choppy/exceptions.py
choppy/exit_code.py
choppy/utils.py
choppy/version.py
choppy/config/__init__.py
choppy/config/choppy-server.conf.example
choppy/config/choppy.conf.example
choppy/config/config.py
choppy/config/schema.py
choppy/config/schemas/config_email.json
choppy/config/schemas/config_general.json
choppy/config/schemas/config_local.json
choppy/config/schemas/config_oss.json
choppy/config/schemas/config_remote.json
choppy/config/schemas/config_repo.json
choppy/config/schemas/config_server.json
choppy/config/schemas/samples.py
choppy/core/__init__.py
choppy/core/app_utils.py
choppy/core/choppy_store.py
choppy/core/cromwell.py
choppy/core/json_checker.py
choppy/core/models.py
choppy/core/monitor.py
choppy/core/oss.py
choppy/core/project_revision.py
choppy/core/scaffold.py
choppy/core/validator.py
choppy/core/workflow.py
choppy/notification/__init__.py
choppy/notification/email_notification.py
choppy/notification/messenger.py
choppy/resources/__init__.py
choppy/resources/cromwell-configfile.template
choppy/resources/cromwell-systemd.template
choppy/resources/dockerfile-shiny.template
choppy/resources/dockerfile.template
choppy/resources/email.template
choppy/resources/mkdocs.yml.template
choppy/resources/multi_wrapper.template
choppy/resources/wrapper.template
choppy/resources/lib/ossutil64
choppy/resources/lib/ossutilmac64
choppy/resources/scaffold_template/README.md
choppy/resources/scaffold_template/defaults
choppy/resources/scaffold_template/inputs
choppy/resources/scaffold_template/workflow.wdl
choppy/resources/scaffold_template/docker/README.md
choppy/resources/scaffold_template/docker/my_program_1/Dockerfile
choppy/resources/scaffold_template/docker/my_program_1/README.md
choppy/resources/scaffold_template/docker/my_program_2/Dockerfile
choppy_pipe.egg-info/PKG-INFO
choppy_pipe.egg-info/SOURCES.txt
choppy_pipe.egg-info/dependency_links.txt
choppy_pipe.egg-info/entry_points.txt
choppy_pipe.egg-info/not-zip-safe
choppy_pipe.egg-info/requires.txt
choppy_pipe.egg-info/top_level.txt
