Metadata-Version: 2.1
Name: choppy-pipe
Version: 0.3.9.dev0
Summary: An integrated analysis platform for efficiently achieving computational reproducibility
Home-page: http://choppy.3steps.cn
Author: Jingcheng Yang
Author-email: yjcyxky@163.com
Maintainer: Choppy Team
Maintainer-email: choppyteam@gmail.com
License: UNKNOWN
Project-URL: Documentation, https://choppy.readthedocs.io
Project-URL: Code, https://github.com/go-choppy/choppy
Project-URL: Issue tracker, https://github.com/go-choppy/choppy/issues
Keywords: choppy,data platform,command-line tool
Platform: any
Classifier: Development Status :: 3 - Alpha
Classifier: Environment :: Console
Classifier: Intended Audience :: Healthcare Industry
Classifier: Intended Audience :: Science/Research
Classifier: Intended Audience :: Developers
Classifier: License :: OSI Approved :: GNU Affero General Public License v3 or later (AGPLv3+)
Classifier: Operating System :: OS Independent
Classifier: Programming Language :: Python :: 3 :: Only
Classifier: Programming Language :: Python :: 3.5
Classifier: Programming Language :: Python :: 3.6
Classifier: Programming Language :: Python :: 3.7
Classifier: Topic :: Scientific/Engineering :: Bio-Informatics
Provides-Extra: dotenv
Provides-Extra: docs
Provides-Extra: dev
